{
  "type": "GROUP",
"name": "All Requests",
"path": "",
"pathFormatted": "group_missing-name-b06d1",
"stats": {
    "name": "All Requests",
    "numberOfRequests": {
        "total": 24,
        "ok": 24,
        "ko": 0
    },
    "minResponseTime": {
        "total": 227,
        "ok": 227,
        "ko": 0
    },
    "maxResponseTime": {
        "total": 3501,
        "ok": 3501,
        "ko": 0
    },
    "meanResponseTime": {
        "total": 1182,
        "ok": 1182,
        "ko": 0
    },
    "standardDeviation": {
        "total": 946,
        "ok": 946,
        "ko": 0
    },
    "percentiles1": {
        "total": 1074,
        "ok": 1074,
        "ko": 0
    },
    "percentiles2": {
        "total": 1474,
        "ok": 1474,
        "ko": 0
    },
    "percentiles3": {
        "total": 3304,
        "ok": 3304,
        "ko": 0
    },
    "percentiles4": {
        "total": 3496,
        "ok": 3496,
        "ko": 0
    },
    "group1": {
    "name": "t < 800 ms",
    "htmlName": "t < 800 ms",
    "count": 10,
    "percentage": 42
},
    "group2": {
    "name": "800 ms <= t < 1200 ms",
    "htmlName": "t >= 800 ms <br> t < 1200 ms",
    "count": 4,
    "percentage": 17
},
    "group3": {
    "name": "t >= 1200 ms",
    "htmlName": "t >= 1200 ms",
    "count": 10,
    "percentage": 42
},
    "group4": {
    "name": "failed",
    "htmlName": "failed",
    "count": 0,
    "percentage": 0
},
    "meanNumberOfRequestsPerSecond": {
        "total": 0.38095238095238093,
        "ok": 0.38095238095238093,
        "ko": 0
    }
},
"contents": {
"req_load-home-page-4f753": {
        "type": "REQUEST",
        "name": "Load Home page",
"path": "Load Home page",
"pathFormatted": "req_load-home-page-4f753",
"stats": {
    "name": "Load Home page",
    "numberOfRequests": {
        "total": 1,
        "ok": 1,
        "ko": 0
    },
    "minResponseTime": {
        "total": 3479,
        "ok": 3479,
        "ko": 0
    },
    "maxResponseTime": {
        "total": 3479,
        "ok": 3479,
        "ko": 0
    },
    "meanResponseTime": {
        "total": 3479,
        "ok": 3479,
        "ko": 0
    },
    "standardDeviation": {
        "total": 0,
        "ok": 0,
        "ko": 0
    },
    "percentiles1": {
        "total": 3479,
        "ok": 3479,
        "ko": 0
    },
    "percentiles2": {
        "total": 3479,
        "ok": 3479,
        "ko": 0
    },
    "percentiles3": {
        "total": 3479,
        "ok": 3479,
        "ko": 0
    },
    "percentiles4": {
        "total": 3479,
        "ok": 3479,
        "ko": 0
    },
    "group1": {
    "name": "t < 800 ms",
    "htmlName": "t < 800 ms",
    "count": 0,
    "percentage": 0
},
    "group2": {
    "name": "800 ms <= t < 1200 ms",
    "htmlName": "t >= 800 ms <br> t < 1200 ms",
    "count": 0,
    "percentage": 0
},
    "group3": {
    "name": "t >= 1200 ms",
    "htmlName": "t >= 1200 ms",
    "count": 1,
    "percentage": 100
},
    "group4": {
    "name": "failed",
    "htmlName": "failed",
    "count": 0,
    "percentage": 0
},
    "meanNumberOfRequestsPerSecond": {
        "total": 0.015873015873015872,
        "ok": 0.015873015873015872,
        "ko": 0
    }
}
    },"req_load-our-story--ded62": {
        "type": "REQUEST",
        "name": "Load our story page",
"path": "Load our story page",
"pathFormatted": "req_load-our-story--ded62",
"stats": {
    "name": "Load our story page",
    "numberOfRequests": {
        "total": 1,
        "ok": 1,
        "ko": 0
    },
    "minResponseTime": {
        "total": 254,
        "ok": 254,
        "ko": 0
    },
    "maxResponseTime": {
        "total": 254,
        "ok": 254,
        "ko": 0
    },
    "meanResponseTime": {
        "total": 254,
        "ok": 254,
        "ko": 0
    },
    "standardDeviation": {
        "total": 0,
        "ok": 0,
        "ko": 0
    },
    "percentiles1": {
        "total": 254,
        "ok": 254,
        "ko": 0
    },
    "percentiles2": {
        "total": 254,
        "ok": 254,
        "ko": 0
    },
    "percentiles3": {
        "total": 254,
        "ok": 254,
        "ko": 0
    },
    "percentiles4": {
        "total": 254,
        "ok": 254,
        "ko": 0
    },
    "group1": {
    "name": "t < 800 ms",
    "htmlName": "t < 800 ms",
    "count": 1,
    "percentage": 100
},
    "group2": {
    "name": "800 ms <= t < 1200 ms",
    "htmlName": "t >= 800 ms <br> t < 1200 ms",
    "count": 0,
    "percentage": 0
},
    "group3": {
    "name": "t >= 1200 ms",
    "htmlName": "t >= 1200 ms",
    "count": 0,
    "percentage": 0
},
    "group4": {
    "name": "failed",
    "htmlName": "failed",
    "count": 0,
    "percentage": 0
},
    "meanNumberOfRequestsPerSecond": {
        "total": 0.015873015873015872,
        "ok": 0.015873015873015872,
        "ko": 0
    }
}
    },"req_load-get-in-tou-41ddb": {
        "type": "REQUEST",
        "name": "Load Get in touch page",
"path": "Load Get in touch page",
"pathFormatted": "req_load-get-in-tou-41ddb",
"stats": {
    "name": "Load Get in touch page",
    "numberOfRequests": {
        "total": 1,
        "ok": 1,
        "ko": 0
    },
    "minResponseTime": {
        "total": 1079,
        "ok": 1079,
        "ko": 0
    },
    "maxResponseTime": {
        "total": 1079,
        "ok": 1079,
        "ko": 0
    },
    "meanResponseTime": {
        "total": 1079,
        "ok": 1079,
        "ko": 0
    },
    "standardDeviation": {
        "total": 0,
        "ok": 0,
        "ko": 0
    },
    "percentiles1": {
        "total": 1079,
        "ok": 1079,
        "ko": 0
    },
    "percentiles2": {
        "total": 1079,
        "ok": 1079,
        "ko": 0
    },
    "percentiles3": {
        "total": 1079,
        "ok": 1079,
        "ko": 0
    },
    "percentiles4": {
        "total": 1079,
        "ok": 1079,
        "ko": 0
    },
    "group1": {
    "name": "t < 800 ms",
    "htmlName": "t < 800 ms",
    "count": 0,
    "percentage": 0
},
    "group2": {
    "name": "800 ms <= t < 1200 ms",
    "htmlName": "t >= 800 ms <br> t < 1200 ms",
    "count": 1,
    "percentage": 100
},
    "group3": {
    "name": "t >= 1200 ms",
    "htmlName": "t >= 1200 ms",
    "count": 0,
    "percentage": 0
},
    "group4": {
    "name": "failed",
    "htmlName": "failed",
    "count": 0,
    "percentage": 0
},
    "meanNumberOfRequestsPerSecond": {
        "total": 0.015873015873015872,
        "ok": 0.015873015873015872,
        "ko": 0
    }
}
    },"req_load-products-l-1e5bd": {
        "type": "REQUEST",
        "name": "Load products list page",
"path": "Load products list page",
"pathFormatted": "req_load-products-l-1e5bd",
"stats": {
    "name": "Load products list page",
    "numberOfRequests": {
        "total": 1,
        "ok": 1,
        "ko": 0
    },
    "minResponseTime": {
        "total": 1068,
        "ok": 1068,
        "ko": 0
    },
    "maxResponseTime": {
        "total": 1068,
        "ok": 1068,
        "ko": 0
    },
    "meanResponseTime": {
        "total": 1068,
        "ok": 1068,
        "ko": 0
    },
    "standardDeviation": {
        "total": 0,
        "ok": 0,
        "ko": 0
    },
    "percentiles1": {
        "total": 1068,
        "ok": 1068,
        "ko": 0
    },
    "percentiles2": {
        "total": 1068,
        "ok": 1068,
        "ko": 0
    },
    "percentiles3": {
        "total": 1068,
        "ok": 1068,
        "ko": 0
    },
    "percentiles4": {
        "total": 1068,
        "ok": 1068,
        "ko": 0
    },
    "group1": {
    "name": "t < 800 ms",
    "htmlName": "t < 800 ms",
    "count": 0,
    "percentage": 0
},
    "group2": {
    "name": "800 ms <= t < 1200 ms",
    "htmlName": "t >= 800 ms <br> t < 1200 ms",
    "count": 1,
    "percentage": 100
},
    "group3": {
    "name": "t >= 1200 ms",
    "htmlName": "t >= 1200 ms",
    "count": 0,
    "percentage": 0
},
    "group4": {
    "name": "failed",
    "htmlName": "failed",
    "count": 0,
    "percentage": 0
},
    "meanNumberOfRequestsPerSecond": {
        "total": 0.015873015873015872,
        "ok": 0.015873015873015872,
        "ko": 0
    }
}
    },"req_load-next-page--08afe": {
        "type": "REQUEST",
        "name": "Load next page of products - Page 1",
"path": "Load next page of products - Page 1",
"pathFormatted": "req_load-next-page--08afe",
"stats": {
    "name": "Load next page of products - Page 1",
    "numberOfRequests": {
        "total": 1,
        "ok": 1,
        "ko": 0
    },
    "minResponseTime": {
        "total": 1238,
        "ok": 1238,
        "ko": 0
    },
    "maxResponseTime": {
        "total": 1238,
        "ok": 1238,
        "ko": 0
    },
    "meanResponseTime": {
        "total": 1238,
        "ok": 1238,
        "ko": 0
    },
    "standardDeviation": {
        "total": 0,
        "ok": 0,
        "ko": 0
    },
    "percentiles1": {
        "total": 1238,
        "ok": 1238,
        "ko": 0
    },
    "percentiles2": {
        "total": 1238,
        "ok": 1238,
        "ko": 0
    },
    "percentiles3": {
        "total": 1238,
        "ok": 1238,
        "ko": 0
    },
    "percentiles4": {
        "total": 1238,
        "ok": 1238,
        "ko": 0
    },
    "group1": {
    "name": "t < 800 ms",
    "htmlName": "t < 800 ms",
    "count": 0,
    "percentage": 0
},
    "group2": {
    "name": "800 ms <= t < 1200 ms",
    "htmlName": "t >= 800 ms <br> t < 1200 ms",
    "count": 0,
    "percentage": 0
},
    "group3": {
    "name": "t >= 1200 ms",
    "htmlName": "t >= 1200 ms",
    "count": 1,
    "percentage": 100
},
    "group4": {
    "name": "failed",
    "htmlName": "failed",
    "count": 0,
    "percentage": 0
},
    "meanNumberOfRequestsPerSecond": {
        "total": 0.015873015873015872,
        "ok": 0.015873015873015872,
        "ko": 0
    }
}
    },"req_load-next-page--177cd": {
        "type": "REQUEST",
        "name": "Load next page of products - Page 2",
"path": "Load next page of products - Page 2",
"pathFormatted": "req_load-next-page--177cd",
"stats": {
    "name": "Load next page of products - Page 2",
    "numberOfRequests": {
        "total": 1,
        "ok": 1,
        "ko": 0
    },
    "minResponseTime": {
        "total": 2311,
        "ok": 2311,
        "ko": 0
    },
    "maxResponseTime": {
        "total": 2311,
        "ok": 2311,
        "ko": 0
    },
    "meanResponseTime": {
        "total": 2311,
        "ok": 2311,
        "ko": 0
    },
    "standardDeviation": {
        "total": 0,
        "ok": 0,
        "ko": 0
    },
    "percentiles1": {
        "total": 2311,
        "ok": 2311,
        "ko": 0
    },
    "percentiles2": {
        "total": 2311,
        "ok": 2311,
        "ko": 0
    },
    "percentiles3": {
        "total": 2311,
        "ok": 2311,
        "ko": 0
    },
    "percentiles4": {
        "total": 2311,
        "ok": 2311,
        "ko": 0
    },
    "group1": {
    "name": "t < 800 ms",
    "htmlName": "t < 800 ms",
    "count": 0,
    "percentage": 0
},
    "group2": {
    "name": "800 ms <= t < 1200 ms",
    "htmlName": "t >= 800 ms <br> t < 1200 ms",
    "count": 0,
    "percentage": 0
},
    "group3": {
    "name": "t >= 1200 ms",
    "htmlName": "t >= 1200 ms",
    "count": 1,
    "percentage": 100
},
    "group4": {
    "name": "failed",
    "htmlName": "failed",
    "count": 0,
    "percentage": 0
},
    "meanNumberOfRequestsPerSecond": {
        "total": 0.015873015873015872,
        "ok": 0.015873015873015872,
        "ko": 0
    }
}
    },"req_load-products-d-91376": {
        "type": "REQUEST",
        "name": "Load products details page - Product : Dart Board",
"path": "Load products details page - Product : Dart Board",
"pathFormatted": "req_load-products-d-91376",
"stats": {
    "name": "Load products details page - Product : Dart Board",
    "numberOfRequests": {
        "total": 1,
        "ok": 1,
        "ko": 0
    },
    "minResponseTime": {
        "total": 656,
        "ok": 656,
        "ko": 0
    },
    "maxResponseTime": {
        "total": 656,
        "ok": 656,
        "ko": 0
    },
    "meanResponseTime": {
        "total": 656,
        "ok": 656,
        "ko": 0
    },
    "standardDeviation": {
        "total": 0,
        "ok": 0,
        "ko": 0
    },
    "percentiles1": {
        "total": 656,
        "ok": 656,
        "ko": 0
    },
    "percentiles2": {
        "total": 656,
        "ok": 656,
        "ko": 0
    },
    "percentiles3": {
        "total": 656,
        "ok": 656,
        "ko": 0
    },
    "percentiles4": {
        "total": 656,
        "ok": 656,
        "ko": 0
    },
    "group1": {
    "name": "t < 800 ms",
    "htmlName": "t < 800 ms",
    "count": 1,
    "percentage": 100
},
    "group2": {
    "name": "800 ms <= t < 1200 ms",
    "htmlName": "t >= 800 ms <br> t < 1200 ms",
    "count": 0,
    "percentage": 0
},
    "group3": {
    "name": "t >= 1200 ms",
    "htmlName": "t >= 1200 ms",
    "count": 0,
    "percentage": 0
},
    "group4": {
    "name": "failed",
    "htmlName": "failed",
    "count": 0,
    "percentage": 0
},
    "meanNumberOfRequestsPerSecond": {
        "total": 0.015873015873015872,
        "ok": 0.015873015873015872,
        "ko": 0
    }
}
    },"req_add-product-to--8f9ec": {
        "type": "REQUEST",
        "name": "Add product to the cart - Product ID:19",
"path": "Add product to the cart - Product ID:19",
"pathFormatted": "req_add-product-to--8f9ec",
"stats": {
    "name": "Add product to the cart - Product ID:19",
    "numberOfRequests": {
        "total": 1,
        "ok": 1,
        "ko": 0
    },
    "minResponseTime": {
        "total": 350,
        "ok": 350,
        "ko": 0
    },
    "maxResponseTime": {
        "total": 350,
        "ok": 350,
        "ko": 0
    },
    "meanResponseTime": {
        "total": 350,
        "ok": 350,
        "ko": 0
    },
    "standardDeviation": {
        "total": 0,
        "ok": 0,
        "ko": 0
    },
    "percentiles1": {
        "total": 350,
        "ok": 350,
        "ko": 0
    },
    "percentiles2": {
        "total": 350,
        "ok": 350,
        "ko": 0
    },
    "percentiles3": {
        "total": 350,
        "ok": 350,
        "ko": 0
    },
    "percentiles4": {
        "total": 350,
        "ok": 350,
        "ko": 0
    },
    "group1": {
    "name": "t < 800 ms",
    "htmlName": "t < 800 ms",
    "count": 1,
    "percentage": 100
},
    "group2": {
    "name": "800 ms <= t < 1200 ms",
    "htmlName": "t >= 800 ms <br> t < 1200 ms",
    "count": 0,
    "percentage": 0
},
    "group3": {
    "name": "t >= 1200 ms",
    "htmlName": "t >= 1200 ms",
    "count": 0,
    "percentage": 0
},
    "group4": {
    "name": "failed",
    "htmlName": "failed",
    "count": 0,
    "percentage": 0
},
    "meanNumberOfRequestsPerSecond": {
        "total": 0.015873015873015872,
        "ok": 0.015873015873015872,
        "ko": 0
    }
}
    },"req_load-products-l-d0955": {
        "type": "REQUEST",
        "name": "Load products list page : Babies Toys",
"path": "Load products list page : Babies Toys",
"pathFormatted": "req_load-products-l-d0955",
"stats": {
    "name": "Load products list page : Babies Toys",
    "numberOfRequests": {
        "total": 1,
        "ok": 1,
        "ko": 0
    },
    "minResponseTime": {
        "total": 3501,
        "ok": 3501,
        "ko": 0
    },
    "maxResponseTime": {
        "total": 3501,
        "ok": 3501,
        "ko": 0
    },
    "meanResponseTime": {
        "total": 3501,
        "ok": 3501,
        "ko": 0
    },
    "standardDeviation": {
        "total": 0,
        "ok": 0,
        "ko": 0
    },
    "percentiles1": {
        "total": 3501,
        "ok": 3501,
        "ko": 0
    },
    "percentiles2": {
        "total": 3501,
        "ok": 3501,
        "ko": 0
    },
    "percentiles3": {
        "total": 3501,
        "ok": 3501,
        "ko": 0
    },
    "percentiles4": {
        "total": 3501,
        "ok": 3501,
        "ko": 0
    },
    "group1": {
    "name": "t < 800 ms",
    "htmlName": "t < 800 ms",
    "count": 0,
    "percentage": 0
},
    "group2": {
    "name": "800 ms <= t < 1200 ms",
    "htmlName": "t >= 800 ms <br> t < 1200 ms",
    "count": 0,
    "percentage": 0
},
    "group3": {
    "name": "t >= 1200 ms",
    "htmlName": "t >= 1200 ms",
    "count": 1,
    "percentage": 100
},
    "group4": {
    "name": "failed",
    "htmlName": "failed",
    "count": 0,
    "percentage": 0
},
    "meanNumberOfRequestsPerSecond": {
        "total": 0.015873015873015872,
        "ok": 0.015873015873015872,
        "ko": 0
    }
}
    },"req_add-product-to--520e0": {
        "type": "REQUEST",
        "name": "Add product to the cart - Product ID:4",
"path": "Add product to the cart - Product ID:4",
"pathFormatted": "req_add-product-to--520e0",
"stats": {
    "name": "Add product to the cart - Product ID:4",
    "numberOfRequests": {
        "total": 2,
        "ok": 2,
        "ko": 0
    },
    "minResponseTime": {
        "total": 1151,
        "ok": 1151,
        "ko": 0
    },
    "maxResponseTime": {
        "total": 1618,
        "ok": 1618,
        "ko": 0
    },
    "meanResponseTime": {
        "total": 1385,
        "ok": 1385,
        "ko": 0
    },
    "standardDeviation": {
        "total": 234,
        "ok": 234,
        "ko": 0
    },
    "percentiles1": {
        "total": 1385,
        "ok": 1385,
        "ko": 0
    },
    "percentiles2": {
        "total": 1501,
        "ok": 1501,
        "ko": 0
    },
    "percentiles3": {
        "total": 1595,
        "ok": 1595,
        "ko": 0
    },
    "percentiles4": {
        "total": 1613,
        "ok": 1613,
        "ko": 0
    },
    "group1": {
    "name": "t < 800 ms",
    "htmlName": "t < 800 ms",
    "count": 0,
    "percentage": 0
},
    "group2": {
    "name": "800 ms <= t < 1200 ms",
    "htmlName": "t >= 800 ms <br> t < 1200 ms",
    "count": 1,
    "percentage": 50
},
    "group3": {
    "name": "t >= 1200 ms",
    "htmlName": "t >= 1200 ms",
    "count": 1,
    "percentage": 50
},
    "group4": {
    "name": "failed",
    "htmlName": "failed",
    "count": 0,
    "percentage": 0
},
    "meanNumberOfRequestsPerSecond": {
        "total": 0.031746031746031744,
        "ok": 0.031746031746031744,
        "ko": 0
    }
}
    },"req_add-product-to--a1ca8": {
        "type": "REQUEST",
        "name": "Add product to the cart - Product ID:2",
"path": "Add product to the cart - Product ID:2",
"pathFormatted": "req_add-product-to--a1ca8",
"stats": {
    "name": "Add product to the cart - Product ID:2",
    "numberOfRequests": {
        "total": 1,
        "ok": 1,
        "ko": 0
    },
    "minResponseTime": {
        "total": 333,
        "ok": 333,
        "ko": 0
    },
    "maxResponseTime": {
        "total": 333,
        "ok": 333,
        "ko": 0
    },
    "meanResponseTime": {
        "total": 333,
        "ok": 333,
        "ko": 0
    },
    "standardDeviation": {
        "total": 0,
        "ok": 0,
        "ko": 0
    },
    "percentiles1": {
        "total": 333,
        "ok": 333,
        "ko": 0
    },
    "percentiles2": {
        "total": 333,
        "ok": 333,
        "ko": 0
    },
    "percentiles3": {
        "total": 333,
        "ok": 333,
        "ko": 0
    },
    "percentiles4": {
        "total": 333,
        "ok": 333,
        "ko": 0
    },
    "group1": {
    "name": "t < 800 ms",
    "htmlName": "t < 800 ms",
    "count": 1,
    "percentage": 100
},
    "group2": {
    "name": "800 ms <= t < 1200 ms",
    "htmlName": "t >= 800 ms <br> t < 1200 ms",
    "count": 0,
    "percentage": 0
},
    "group3": {
    "name": "t >= 1200 ms",
    "htmlName": "t >= 1200 ms",
    "count": 0,
    "percentage": 0
},
    "group4": {
    "name": "failed",
    "htmlName": "failed",
    "count": 0,
    "percentage": 0
},
    "meanNumberOfRequestsPerSecond": {
        "total": 0.015873015873015872,
        "ok": 0.015873015873015872,
        "ko": 0
    }
}
    },"req_view-cart-59fc6": {
        "type": "REQUEST",
        "name": "View Cart",
"path": "View Cart",
"pathFormatted": "req_view-cart-59fc6",
"stats": {
    "name": "View Cart",
    "numberOfRequests": {
        "total": 1,
        "ok": 1,
        "ko": 0
    },
    "minResponseTime": {
        "total": 247,
        "ok": 247,
        "ko": 0
    },
    "maxResponseTime": {
        "total": 247,
        "ok": 247,
        "ko": 0
    },
    "meanResponseTime": {
        "total": 247,
        "ok": 247,
        "ko": 0
    },
    "standardDeviation": {
        "total": 0,
        "ok": 0,
        "ko": 0
    },
    "percentiles1": {
        "total": 247,
        "ok": 247,
        "ko": 0
    },
    "percentiles2": {
        "total": 247,
        "ok": 247,
        "ko": 0
    },
    "percentiles3": {
        "total": 247,
        "ok": 247,
        "ko": 0
    },
    "percentiles4": {
        "total": 247,
        "ok": 247,
        "ko": 0
    },
    "group1": {
    "name": "t < 800 ms",
    "htmlName": "t < 800 ms",
    "count": 1,
    "percentage": 100
},
    "group2": {
    "name": "800 ms <= t < 1200 ms",
    "htmlName": "t >= 800 ms <br> t < 1200 ms",
    "count": 0,
    "percentage": 0
},
    "group3": {
    "name": "t >= 1200 ms",
    "htmlName": "t >= 1200 ms",
    "count": 0,
    "percentage": 0
},
    "group4": {
    "name": "failed",
    "htmlName": "failed",
    "count": 0,
    "percentage": 0
},
    "meanNumberOfRequestsPerSecond": {
        "total": 0.015873015873015872,
        "ok": 0.015873015873015872,
        "ko": 0
    }
}
    },"req_view-cart-redir-79e0c": {
        "type": "REQUEST",
        "name": "View Cart Redirect 1",
"path": "View Cart Redirect 1",
"pathFormatted": "req_view-cart-redir-79e0c",
"stats": {
    "name": "View Cart Redirect 1",
    "numberOfRequests": {
        "total": 1,
        "ok": 1,
        "ko": 0
    },
    "minResponseTime": {
        "total": 557,
        "ok": 557,
        "ko": 0
    },
    "maxResponseTime": {
        "total": 557,
        "ok": 557,
        "ko": 0
    },
    "meanResponseTime": {
        "total": 557,
        "ok": 557,
        "ko": 0
    },
    "standardDeviation": {
        "total": 0,
        "ok": 0,
        "ko": 0
    },
    "percentiles1": {
        "total": 557,
        "ok": 557,
        "ko": 0
    },
    "percentiles2": {
        "total": 557,
        "ok": 557,
        "ko": 0
    },
    "percentiles3": {
        "total": 557,
        "ok": 557,
        "ko": 0
    },
    "percentiles4": {
        "total": 557,
        "ok": 557,
        "ko": 0
    },
    "group1": {
    "name": "t < 800 ms",
    "htmlName": "t < 800 ms",
    "count": 1,
    "percentage": 100
},
    "group2": {
    "name": "800 ms <= t < 1200 ms",
    "htmlName": "t >= 800 ms <br> t < 1200 ms",
    "count": 0,
    "percentage": 0
},
    "group3": {
    "name": "t >= 1200 ms",
    "htmlName": "t >= 1200 ms",
    "count": 0,
    "percentage": 0
},
    "group4": {
    "name": "failed",
    "htmlName": "failed",
    "count": 0,
    "percentage": 0
},
    "meanNumberOfRequestsPerSecond": {
        "total": 0.015873015873015872,
        "ok": 0.015873015873015872,
        "ko": 0
    }
}
    },"req_login-user-206f1": {
        "type": "REQUEST",
        "name": "Login User",
"path": "Login User",
"pathFormatted": "req_login-user-206f1",
"stats": {
    "name": "Login User",
    "numberOfRequests": {
        "total": 1,
        "ok": 1,
        "ko": 0
    },
    "minResponseTime": {
        "total": 309,
        "ok": 309,
        "ko": 0
    },
    "maxResponseTime": {
        "total": 309,
        "ok": 309,
        "ko": 0
    },
    "meanResponseTime": {
        "total": 309,
        "ok": 309,
        "ko": 0
    },
    "standardDeviation": {
        "total": 0,
        "ok": 0,
        "ko": 0
    },
    "percentiles1": {
        "total": 309,
        "ok": 309,
        "ko": 0
    },
    "percentiles2": {
        "total": 309,
        "ok": 309,
        "ko": 0
    },
    "percentiles3": {
        "total": 309,
        "ok": 309,
        "ko": 0
    },
    "percentiles4": {
        "total": 309,
        "ok": 309,
        "ko": 0
    },
    "group1": {
    "name": "t < 800 ms",
    "htmlName": "t < 800 ms",
    "count": 1,
    "percentage": 100
},
    "group2": {
    "name": "800 ms <= t < 1200 ms",
    "htmlName": "t >= 800 ms <br> t < 1200 ms",
    "count": 0,
    "percentage": 0
},
    "group3": {
    "name": "t >= 1200 ms",
    "htmlName": "t >= 1200 ms",
    "count": 0,
    "percentage": 0
},
    "group4": {
    "name": "failed",
    "htmlName": "failed",
    "count": 0,
    "percentage": 0
},
    "meanNumberOfRequestsPerSecond": {
        "total": 0.015873015873015872,
        "ok": 0.015873015873015872,
        "ko": 0
    }
}
    },"req_login-user-redi-c35c5": {
        "type": "REQUEST",
        "name": "Login User Redirect 1",
"path": "Login User Redirect 1",
"pathFormatted": "req_login-user-redi-c35c5",
"stats": {
    "name": "Login User Redirect 1",
    "numberOfRequests": {
        "total": 1,
        "ok": 1,
        "ko": 0
    },
    "minResponseTime": {
        "total": 2252,
        "ok": 2252,
        "ko": 0
    },
    "maxResponseTime": {
        "total": 2252,
        "ok": 2252,
        "ko": 0
    },
    "meanResponseTime": {
        "total": 2252,
        "ok": 2252,
        "ko": 0
    },
    "standardDeviation": {
        "total": 0,
        "ok": 0,
        "ko": 0
    },
    "percentiles1": {
        "total": 2252,
        "ok": 2252,
        "ko": 0
    },
    "percentiles2": {
        "total": 2252,
        "ok": 2252,
        "ko": 0
    },
    "percentiles3": {
        "total": 2252,
        "ok": 2252,
        "ko": 0
    },
    "percentiles4": {
        "total": 2252,
        "ok": 2252,
        "ko": 0
    },
    "group1": {
    "name": "t < 800 ms",
    "htmlName": "t < 800 ms",
    "count": 0,
    "percentage": 0
},
    "group2": {
    "name": "800 ms <= t < 1200 ms",
    "htmlName": "t >= 800 ms <br> t < 1200 ms",
    "count": 0,
    "percentage": 0
},
    "group3": {
    "name": "t >= 1200 ms",
    "htmlName": "t >= 1200 ms",
    "count": 1,
    "percentage": 100
},
    "group4": {
    "name": "failed",
    "htmlName": "failed",
    "count": 0,
    "percentage": 0
},
    "meanNumberOfRequestsPerSecond": {
        "total": 0.015873015873015872,
        "ok": 0.015873015873015872,
        "ko": 0
    }
}
    },"req_increase-produc-c8d60": {
        "type": "REQUEST",
        "name": "Increase product Quantity : Product Id : 19",
"path": "Increase product Quantity : Product Id : 19",
"pathFormatted": "req_increase-produc-c8d60",
"stats": {
    "name": "Increase product Quantity : Product Id : 19",
    "numberOfRequests": {
        "total": 1,
        "ok": 1,
        "ko": 0
    },
    "minResponseTime": {
        "total": 227,
        "ok": 227,
        "ko": 0
    },
    "maxResponseTime": {
        "total": 227,
        "ok": 227,
        "ko": 0
    },
    "meanResponseTime": {
        "total": 227,
        "ok": 227,
        "ko": 0
    },
    "standardDeviation": {
        "total": 0,
        "ok": 0,
        "ko": 0
    },
    "percentiles1": {
        "total": 227,
        "ok": 227,
        "ko": 0
    },
    "percentiles2": {
        "total": 227,
        "ok": 227,
        "ko": 0
    },
    "percentiles3": {
        "total": 227,
        "ok": 227,
        "ko": 0
    },
    "percentiles4": {
        "total": 227,
        "ok": 227,
        "ko": 0
    },
    "group1": {
    "name": "t < 800 ms",
    "htmlName": "t < 800 ms",
    "count": 1,
    "percentage": 100
},
    "group2": {
    "name": "800 ms <= t < 1200 ms",
    "htmlName": "t >= 800 ms <br> t < 1200 ms",
    "count": 0,
    "percentage": 0
},
    "group3": {
    "name": "t >= 1200 ms",
    "htmlName": "t >= 1200 ms",
    "count": 0,
    "percentage": 0
},
    "group4": {
    "name": "failed",
    "htmlName": "failed",
    "count": 0,
    "percentage": 0
},
    "meanNumberOfRequestsPerSecond": {
        "total": 0.015873015873015872,
        "ok": 0.015873015873015872,
        "ko": 0
    }
}
    },"req_increase-produc-da4bf": {
        "type": "REQUEST",
        "name": "Increase product Quantity : Product Id : 19 Redirect 1",
"path": "Increase product Quantity : Product Id : 19 Redirect 1",
"pathFormatted": "req_increase-produc-da4bf",
"stats": {
    "name": "Increase product Quantity : Product Id : 19 Redirect 1",
    "numberOfRequests": {
        "total": 1,
        "ok": 1,
        "ko": 0
    },
    "minResponseTime": {
        "total": 1321,
        "ok": 1321,
        "ko": 0
    },
    "maxResponseTime": {
        "total": 1321,
        "ok": 1321,
        "ko": 0
    },
    "meanResponseTime": {
        "total": 1321,
        "ok": 1321,
        "ko": 0
    },
    "standardDeviation": {
        "total": 0,
        "ok": 0,
        "ko": 0
    },
    "percentiles1": {
        "total": 1321,
        "ok": 1321,
        "ko": 0
    },
    "percentiles2": {
        "total": 1321,
        "ok": 1321,
        "ko": 0
    },
    "percentiles3": {
        "total": 1321,
        "ok": 1321,
        "ko": 0
    },
    "percentiles4": {
        "total": 1321,
        "ok": 1321,
        "ko": 0
    },
    "group1": {
    "name": "t < 800 ms",
    "htmlName": "t < 800 ms",
    "count": 0,
    "percentage": 0
},
    "group2": {
    "name": "800 ms <= t < 1200 ms",
    "htmlName": "t >= 800 ms <br> t < 1200 ms",
    "count": 0,
    "percentage": 0
},
    "group3": {
    "name": "t >= 1200 ms",
    "htmlName": "t >= 1200 ms",
    "count": 1,
    "percentage": 100
},
    "group4": {
    "name": "failed",
    "htmlName": "failed",
    "count": 0,
    "percentage": 0
},
    "meanNumberOfRequestsPerSecond": {
        "total": 0.015873015873015872,
        "ok": 0.015873015873015872,
        "ko": 0
    }
}
    },"req_decrease-produc-45349": {
        "type": "REQUEST",
        "name": "Decrease product Quantity : Product Id : 4",
"path": "Decrease product Quantity : Product Id : 4",
"pathFormatted": "req_decrease-produc-45349",
"stats": {
    "name": "Decrease product Quantity : Product Id : 4",
    "numberOfRequests": {
        "total": 1,
        "ok": 1,
        "ko": 0
    },
    "minResponseTime": {
        "total": 877,
        "ok": 877,
        "ko": 0
    },
    "maxResponseTime": {
        "total": 877,
        "ok": 877,
        "ko": 0
    },
    "meanResponseTime": {
        "total": 877,
        "ok": 877,
        "ko": 0
    },
    "standardDeviation": {
        "total": 0,
        "ok": 0,
        "ko": 0
    },
    "percentiles1": {
        "total": 877,
        "ok": 877,
        "ko": 0
    },
    "percentiles2": {
        "total": 877,
        "ok": 877,
        "ko": 0
    },
    "percentiles3": {
        "total": 877,
        "ok": 877,
        "ko": 0
    },
    "percentiles4": {
        "total": 877,
        "ok": 877,
        "ko": 0
    },
    "group1": {
    "name": "t < 800 ms",
    "htmlName": "t < 800 ms",
    "count": 0,
    "percentage": 0
},
    "group2": {
    "name": "800 ms <= t < 1200 ms",
    "htmlName": "t >= 800 ms <br> t < 1200 ms",
    "count": 1,
    "percentage": 100
},
    "group3": {
    "name": "t >= 1200 ms",
    "htmlName": "t >= 1200 ms",
    "count": 0,
    "percentage": 0
},
    "group4": {
    "name": "failed",
    "htmlName": "failed",
    "count": 0,
    "percentage": 0
},
    "meanNumberOfRequestsPerSecond": {
        "total": 0.015873015873015872,
        "ok": 0.015873015873015872,
        "ko": 0
    }
}
    },"req_decrease-produc-36a55": {
        "type": "REQUEST",
        "name": "Decrease product Quantity : Product Id : 4 Redirect 1",
"path": "Decrease product Quantity : Product Id : 4 Redirect 1",
"pathFormatted": "req_decrease-produc-36a55",
"stats": {
    "name": "Decrease product Quantity : Product Id : 4 Redirect 1",
    "numberOfRequests": {
        "total": 1,
        "ok": 1,
        "ko": 0
    },
    "minResponseTime": {
        "total": 2151,
        "ok": 2151,
        "ko": 0
    },
    "maxResponseTime": {
        "total": 2151,
        "ok": 2151,
        "ko": 0
    },
    "meanResponseTime": {
        "total": 2151,
        "ok": 2151,
        "ko": 0
    },
    "standardDeviation": {
        "total": 0,
        "ok": 0,
        "ko": 0
    },
    "percentiles1": {
        "total": 2151,
        "ok": 2151,
        "ko": 0
    },
    "percentiles2": {
        "total": 2151,
        "ok": 2151,
        "ko": 0
    },
    "percentiles3": {
        "total": 2151,
        "ok": 2151,
        "ko": 0
    },
    "percentiles4": {
        "total": 2151,
        "ok": 2151,
        "ko": 0
    },
    "group1": {
    "name": "t < 800 ms",
    "htmlName": "t < 800 ms",
    "count": 0,
    "percentage": 0
},
    "group2": {
    "name": "800 ms <= t < 1200 ms",
    "htmlName": "t >= 800 ms <br> t < 1200 ms",
    "count": 0,
    "percentage": 0
},
    "group3": {
    "name": "t >= 1200 ms",
    "htmlName": "t >= 1200 ms",
    "count": 1,
    "percentage": 100
},
    "group4": {
    "name": "failed",
    "htmlName": "failed",
    "count": 0,
    "percentage": 0
},
    "meanNumberOfRequestsPerSecond": {
        "total": 0.015873015873015872,
        "ok": 0.015873015873015872,
        "ko": 0
    }
}
    },"req_cart-checkout-3684b": {
        "type": "REQUEST",
        "name": "Cart checkout",
"path": "Cart checkout",
"pathFormatted": "req_cart-checkout-3684b",
"stats": {
    "name": "Cart checkout",
    "numberOfRequests": {
        "total": 1,
        "ok": 1,
        "ko": 0
    },
    "minResponseTime": {
        "total": 281,
        "ok": 281,
        "ko": 0
    },
    "maxResponseTime": {
        "total": 281,
        "ok": 281,
        "ko": 0
    },
    "meanResponseTime": {
        "total": 281,
        "ok": 281,
        "ko": 0
    },
    "standardDeviation": {
        "total": 0,
        "ok": 0,
        "ko": 0
    },
    "percentiles1": {
        "total": 281,
        "ok": 281,
        "ko": 0
    },
    "percentiles2": {
        "total": 281,
        "ok": 281,
        "ko": 0
    },
    "percentiles3": {
        "total": 281,
        "ok": 281,
        "ko": 0
    },
    "percentiles4": {
        "total": 281,
        "ok": 281,
        "ko": 0
    },
    "group1": {
    "name": "t < 800 ms",
    "htmlName": "t < 800 ms",
    "count": 1,
    "percentage": 100
},
    "group2": {
    "name": "800 ms <= t < 1200 ms",
    "htmlName": "t >= 800 ms <br> t < 1200 ms",
    "count": 0,
    "percentage": 0
},
    "group3": {
    "name": "t >= 1200 ms",
    "htmlName": "t >= 1200 ms",
    "count": 0,
    "percentage": 0
},
    "group4": {
    "name": "failed",
    "htmlName": "failed",
    "count": 0,
    "percentage": 0
},
    "meanNumberOfRequestsPerSecond": {
        "total": 0.015873015873015872,
        "ok": 0.015873015873015872,
        "ko": 0
    }
}
    },"req_cart-checkout-r-ac1a5": {
        "type": "REQUEST",
        "name": "Cart checkout Redirect 1",
"path": "Cart checkout Redirect 1",
"pathFormatted": "req_cart-checkout-r-ac1a5",
"stats": {
    "name": "Cart checkout Redirect 1",
    "numberOfRequests": {
        "total": 1,
        "ok": 1,
        "ko": 0
    },
    "minResponseTime": {
        "total": 1426,
        "ok": 1426,
        "ko": 0
    },
    "maxResponseTime": {
        "total": 1426,
        "ok": 1426,
        "ko": 0
    },
    "meanResponseTime": {
        "total": 1426,
        "ok": 1426,
        "ko": 0
    },
    "standardDeviation": {
        "total": 0,
        "ok": 0,
        "ko": 0
    },
    "percentiles1": {
        "total": 1426,
        "ok": 1426,
        "ko": 0
    },
    "percentiles2": {
        "total": 1426,
        "ok": 1426,
        "ko": 0
    },
    "percentiles3": {
        "total": 1426,
        "ok": 1426,
        "ko": 0
    },
    "percentiles4": {
        "total": 1426,
        "ok": 1426,
        "ko": 0
    },
    "group1": {
    "name": "t < 800 ms",
    "htmlName": "t < 800 ms",
    "count": 0,
    "percentage": 0
},
    "group2": {
    "name": "800 ms <= t < 1200 ms",
    "htmlName": "t >= 800 ms <br> t < 1200 ms",
    "count": 0,
    "percentage": 0
},
    "group3": {
    "name": "t >= 1200 ms",
    "htmlName": "t >= 1200 ms",
    "count": 1,
    "percentage": 100
},
    "group4": {
    "name": "failed",
    "htmlName": "failed",
    "count": 0,
    "percentage": 0
},
    "meanNumberOfRequestsPerSecond": {
        "total": 0.015873015873015872,
        "ok": 0.015873015873015872,
        "ko": 0
    }
}
    },"req_logout-0323d": {
        "type": "REQUEST",
        "name": "Logout",
"path": "Logout",
"pathFormatted": "req_logout-0323d",
"stats": {
    "name": "Logout",
    "numberOfRequests": {
        "total": 1,
        "ok": 1,
        "ko": 0
    },
    "minResponseTime": {
        "total": 325,
        "ok": 325,
        "ko": 0
    },
    "maxResponseTime": {
        "total": 325,
        "ok": 325,
        "ko": 0
    },
    "meanResponseTime": {
        "total": 325,
        "ok": 325,
        "ko": 0
    },
    "standardDeviation": {
        "total": 0,
        "ok": 0,
        "ko": 0
    },
    "percentiles1": {
        "total": 325,
        "ok": 325,
        "ko": 0
    },
    "percentiles2": {
        "total": 325,
        "ok": 325,
        "ko": 0
    },
    "percentiles3": {
        "total": 325,
        "ok": 325,
        "ko": 0
    },
    "percentiles4": {
        "total": 325,
        "ok": 325,
        "ko": 0
    },
    "group1": {
    "name": "t < 800 ms",
    "htmlName": "t < 800 ms",
    "count": 1,
    "percentage": 100
},
    "group2": {
    "name": "800 ms <= t < 1200 ms",
    "htmlName": "t >= 800 ms <br> t < 1200 ms",
    "count": 0,
    "percentage": 0
},
    "group3": {
    "name": "t >= 1200 ms",
    "htmlName": "t >= 1200 ms",
    "count": 0,
    "percentage": 0
},
    "group4": {
    "name": "failed",
    "htmlName": "failed",
    "count": 0,
    "percentage": 0
},
    "meanNumberOfRequestsPerSecond": {
        "total": 0.015873015873015872,
        "ok": 0.015873015873015872,
        "ko": 0
    }
}
    },"req_logout-redirect-937a3": {
        "type": "REQUEST",
        "name": "Logout Redirect 1",
"path": "Logout Redirect 1",
"pathFormatted": "req_logout-redirect-937a3",
"stats": {
    "name": "Logout Redirect 1",
    "numberOfRequests": {
        "total": 1,
        "ok": 1,
        "ko": 0
    },
    "minResponseTime": {
        "total": 1367,
        "ok": 1367,
        "ko": 0
    },
    "maxResponseTime": {
        "total": 1367,
        "ok": 1367,
        "ko": 0
    },
    "meanResponseTime": {
        "total": 1367,
        "ok": 1367,
        "ko": 0
    },
    "standardDeviation": {
        "total": 0,
        "ok": 0,
        "ko": 0
    },
    "percentiles1": {
        "total": 1367,
        "ok": 1367,
        "ko": 0
    },
    "percentiles2": {
        "total": 1367,
        "ok": 1367,
        "ko": 0
    },
    "percentiles3": {
        "total": 1367,
        "ok": 1367,
        "ko": 0
    },
    "percentiles4": {
        "total": 1367,
        "ok": 1367,
        "ko": 0
    },
    "group1": {
    "name": "t < 800 ms",
    "htmlName": "t < 800 ms",
    "count": 0,
    "percentage": 0
},
    "group2": {
    "name": "800 ms <= t < 1200 ms",
    "htmlName": "t >= 800 ms <br> t < 1200 ms",
    "count": 0,
    "percentage": 0
},
    "group3": {
    "name": "t >= 1200 ms",
    "htmlName": "t >= 1200 ms",
    "count": 1,
    "percentage": 100
},
    "group4": {
    "name": "failed",
    "htmlName": "failed",
    "count": 0,
    "percentage": 0
},
    "meanNumberOfRequestsPerSecond": {
        "total": 0.015873015873015872,
        "ok": 0.015873015873015872,
        "ko": 0
    }
}
    }
}

}